chai_one/__init__.py
chai_one/model.py
chai_one-0.0.2.dist-info/LICENSE
chai_one-0.0.2.dist-info/METADATA
chai_one-0.0.2.dist-info/WHEEL
chai_one-0.0.2.dist-info/RECORD
